websockets_groups/__init__.py
websockets_groups/connects.py
websockets_groups/dispatchers.py
websockets_groups/managers.py
websockets_groups/storages/__init__.py
websockets_groups/storages/base.py
websockets_groups/storages/memory.py
websockets_groups/storages/redis.py
websockets_groups-0.0.2a1.dist-info/LICENSE
websockets_groups-0.0.2a1.dist-info/METADATA
websockets_groups-0.0.2a1.dist-info/WHEEL
websockets_groups-0.0.2a1.dist-info/RECORD
